DeepMail/Mail.py
DeepMail-0.1.1.dist-info/LICENSE.txt
DeepMail-0.1.1.dist-info/METADATA
DeepMail-0.1.1.dist-info/WHEEL
DeepMail-0.1.1.dist-info/top_level.txt
DeepMail-0.1.1.dist-info/RECORD
