Metadata-Version: 2.1
Name: DeepMail
Version: 0.1.1
Summary: For mail Deep learning
Home-page: https://github.com/saichandrareddy1/MailSender
Author: SaiReddy
Author-email: vsaichandrareddy@gmail.com
License: MIT
Download-URL: https://github.com/saichandrareddy1/MailSender/archive/v_01.tar.gz
Keywords: Mail,DeepLearning,Sending
Platform: UNKNOWN
Classifier: Development Status :: 3 - Alpha
Classifier: Intended Audience :: Developers
Classifier: Topic :: Software Development :: Build Tools
Classifier: License :: OSI Approved :: MIT License
Classifier: Programming Language :: Python :: 3
Classifier: Programming Language :: Python :: 3.4
Classifier: Programming Language :: Python :: 3.5
Classifier: Programming Language :: Python :: 3.6
Classifier: Programming Language :: Python :: 3.7
